{
    "My Behavior": {
        "checkpoints": [
            {
                "steps": 499987,
                "file_path": "results\\Direction00000\\My Behavior\\My Behavior-499987.onnx",
                "reward": null,
                "creation_time": 1669639387.0535014,
                "auxillary_file_paths": [
                    "results\\Direction00000\\My Behavior\\My Behavior-499987.pt"
                ]
            },
            {
                "steps": 999963,
                "file_path": "results\\Direction00000\\My Behavior\\My Behavior-999963.onnx",
                "reward": 27.254476457834244,
                "creation_time": 1669639699.5241933,
                "auxillary_file_paths": [
                    "results\\Direction00000\\My Behavior\\My Behavior-999963.pt"
                ]
            },
            {
                "steps": 1499970,
                "file_path": "results\\Direction00000\\My Behavior\\My Behavior-1499970.onnx",
                "reward": 25.27626913636923,
                "creation_time": 1669640010.5720487,
                "auxillary_file_paths": [
                    "results\\Direction00000\\My Behavior\\My Behavior-1499970.pt"
                ]
            },
            {
                "steps": 1500034,
                "file_path": "results\\Direction00000\\My Behavior\\My Behavior-1500034.onnx",
                "reward": 25.27626913636923,
                "creation_time": 1669640010.626948,
                "auxillary_file_paths": [
                    "results\\Direction00000\\My Behavior\\My Behavior-1500034.pt"
                ]
            }
        ],
        "final_checkpoint": {
            "steps": 1500034,
            "file_path": "results\\Direction00000\\My Behavior.onnx",
            "reward": 25.27626913636923,
            "creation_time": 1669640010.626948,
            "auxillary_file_paths": [
                "results\\Direction00000\\My Behavior\\My Behavior-1500034.pt"
            ]
        }
    },
    "metadata": {
        "stats_format_version": "0.3.0",
        "mlagents_version": "0.29.0",
        "torch_version": "1.7.1+cu110"
    }
}